planetcasio/__init__.py
planetcasio/__main__.py
planetcasio/account.py
planetcasio/bbcode.py
planetcasio/cli.py
planetcasio/client.py
planetcasio/errors.py
planetcasio/misc.py
planetcasio/programs.py
planetcasio/shout.py
planetcasio/transport.py
planetcasio/user_profiles.py
planetcasio-0.5.dist-info/METADATA
planetcasio-0.5.dist-info/WHEEL
planetcasio-0.5.dist-info/entry_points.txt
planetcasio-0.5.dist-info/licenses/LICENSE.txt
planetcasio-0.5.dist-info/RECORD
